MANIFEST.in
setup.py
pqaut/__init__.py
pqaut/clicker.py
pqaut/client.py
pqaut/key_press.py
pqaut/server.py
pqaut.egg-info/PKG-INFO
pqaut.egg-info/SOURCES.txt
pqaut.egg-info/dependency_links.txt
pqaut.egg-info/requires.txt
pqaut.egg-info/top_level.txt
pqaut/automator/__init__.py
pqaut/automator/factory.py
pqaut/automator/qobject.py
pqaut/automator/qquickitem.py
pqaut/automator/qquickwidget.py
pqaut/automator/qquickwindow.py
pqaut/automator/qwidget.py