Metadata-Version: 1.0
Name: pqaut
Version: 0.3.9
Summary: Automation for BDD testing PyQt apps
Home-page: UNKNOWN
Author: Gary Johnson
Author-email: gary@gjtt.com
License: MIT License
Platform: UNKNOWN
